LICENSE
MANIFEST.in
README.md
setup.cfg
setup.py
acpy.egg-info/PKG-INFO
acpy.egg-info/SOURCES.txt
acpy.egg-info/dependency_links.txt
acpy.egg-info/entry_points.txt
acpy.egg-info/requires.txt
acpy.egg-info/top_level.txt
api/__init__.py
api/admin.py
api/auth.py
api/group.py
api/resource.py
api/user.py