Metadata-Version: 1.2
Name: acpy
Version: 0.5
Summary: Accounting Center API
Home-page: https://github.com/uzh/acpy
Author: Pim Witlox
Author-email: pim.witlox@uzh.ch
License: GPLv3
Project-URL: Documentation, https://acpy.readthedocs.io/en/latest/
Project-URL: Source, https://github.com/uzh/acpy/
Project-URL: Tracker, https://github.com/uzh/acpy/issues
Keywords: Web,Python,Python3,REST
Platform: UNKNOWN
Classifier: Development Status :: 3 - Alpha
Classifier: Intended Audience :: System Administrators
Classifier: Natural Language :: English
Classifier: Environment :: Console
Classifier: License :: OSI Approved :: MIT License
Classifier: Programming Language :: Python
Classifier: Programming Language :: Python :: 3
Classifier: Programming Language :: Python :: 3.5
Classifier: Programming Language :: Python :: 3.6
Classifier: Topic :: Software Development :: Libraries
Classifier: Topic :: Utilities
Requires-Python: >=3.5
